dagster_cli/__init__.py
dagster_cli/__main__.py
dagster_cli/auth.py
dagster_cli/cli.py
dagster_cli/client.py
dagster_cli/commands/__init__.py
dagster_cli/commands/asset.py
dagster_cli/commands/automation.py
dagster_cli/commands/deployment.py
dagster_cli/commands/job.py
dagster_cli/commands/mcp.py
dagster_cli/commands/repo.py
dagster_cli/commands/run.py
dagster_cli/config.py
dagster_cli/constants.py
dagster_cli/mcp_server.py
dagster_cli/utils/__init__.py
dagster_cli/utils/errors.py
dagster_cli/utils/output.py
dagster_cli/utils/run_utils.py
dagster_cli/utils/tldr.py
dagster_cli-0.8.1.dist-info/licenses/LICENSE
dagster_cli-0.8.1.dist-info/WHEEL
dagster_cli-0.8.1.dist-info/entry_points.txt
dagster_cli-0.8.1.dist-info/METADATA
dagster_cli-0.8.1.dist-info/RECORD
