Metadata-Version: 2.4
Name: dagster-cli
Version: 0.8.1
Summary: A command-line interface for Dagster+
Keywords: dagster,cli,dagster-plus,dagster-cloud
Author: Pedro
Author-email: Pedro <me@pdbr.org>
License-Expression: MIT
License-File: LICENSE
Classifier: Development Status :: 3 - Alpha
Classifier: Intended Audience :: Developers
Classifier: Programming Language :: Python :: 3
Classifier: Programming Language :: Python :: 3.10
Classifier: Programming Language :: Python :: 3.11
Classifier: Programming Language :: Python :: 3.12
Classifier: Programming Language :: Python :: 3.13
Requires-Dist: typer>=0.9.0
Requires-Dist: dagster-graphql>=1.8.13
Requires-Dist: gql[requests]>=3.5.3
Requires-Dist: python-dotenv>=1.0.1
Requires-Dist: rich>=13.0.0
Requires-Dist: mcp[cli]>=1.2.0
Requires-Dist: uvicorn>=0.30.0
Requires-Python: >=3.10
